probe_design/__init__.py
probe_design/data/exclude/excl_roi_1.bed
probe_design/data/exclude/excl_roi_10.bed
probe_design/data/exclude/excl_roi_11.bed
probe_design/data/exclude/excl_roi_12.bed
probe_design/data/exclude/excl_roi_2.bed
probe_design/data/exclude/excl_roi_3.bed
probe_design/data/exclude/excl_roi_4.bed
probe_design/data/exclude/excl_roi_5.bed
probe_design/data/exclude/excl_roi_6.bed
probe_design/data/exclude/excl_roi_7.bed
probe_design/data/exclude/excl_roi_8.bed
probe_design/data/exclude/excl_roi_9.bed
probe_design/data/rois/DNA_FISH_template.ods
probe_design/data/rois/DNA_RNA_FISH_template.ods
probe_design/data/rois/RNA_FISH_template.ods
probe_design/data/rois/all_regions.tsv
probe_design/data/rois/df_DNA_FISH.txt
probe_design/data/rois/df_DNA_RNA_FISH.txt
probe_design/data/rois/df_RNA_FISH.txt
probe_design/main.py
probe_design/notebooks/plot_oligos.ipynb
probe_design/notebooks/plot_probe_candidates.ipynb
probe_design/notebooks/plot_probes.ipynb
probe_design/shell/apply_blacklist.sh
probe_design/shell/build-db.sh
probe_design/shell/build-db_BL.sh
probe_design/shell/build-db_cc.sh
probe_design/shell/generate_blacklist.sh
probe_design/shell/genome_upper.sh
probe_design/shell/get_T2T.sh
probe_design/shell/get_ref_genome.sh
probe_design/shell/makedirs.sh
probe_design/shell/melt_secs_parallel.sh
probe_design/shell/pipeline.sh
probe_design/shell/pipeline_exclude.sh
probe_design/shell/probe-query.sh
probe_design/shell/ref2upper.sh
probe_design/shell/run_nHUSH.sh
probe_design/shell/run_nHUSH_excl.sh
probe_design/shell/show.sh
probe_design/shell/test_shell.sh
probe_design/shell/unfinished_HUSH.sh
probe_design/shell/validation_oldHUSH_BLAST.sh
probe_design/src/HUSH_feedback.py
probe_design/src/__init__.py
probe_design/src/cycling_query.py
probe_design/src/cycling_query_new.py
probe_design/src/download_chromosomes.py
probe_design/src/ensemble.py
probe_design/src/escafish_score.py
probe_design/src/escafish_score_new.py
probe_design/src/exclude_region.py
probe_design-0.2.45.dist-info/LICENSE
probe_design-0.2.45.dist-info/METADATA
probe_design-0.2.45.dist-info/WHEEL
probe_design-0.2.45.dist-info/entry_points.txt
probe_design-0.2.45.dist-info/RECORD
