Metadata-Version: 2.1
Name: probe-design
Version: 0.2.45
Summary: Probe design for FISH by Quentin Verron
Home-page: https://github.com/qverron/probe_design
License: CC NC BY 4.0
Keywords: FISH,probe,design,bioinformatics
Author: Quentin Verron
Maintainer: Quentin Verron
Maintainer-email: quentin.verron@ki.se
Requires-Python: >=3.10,<4.0
Classifier: License :: Other/Proprietary License
Classifier: Programming Language :: Python :: 3
Classifier: Programming Language :: Python :: 3.10
Classifier: Programming Language :: Python :: 3.11
Classifier: Programming Language :: Python :: 3.12
Requires-Dist: beautifulsoup4 (>=4.12.3,<5.0.0)
Requires-Dist: biopython (>=1.82,<2.0)
Requires-Dist: cairosvg (>=2.7.1,<3.0.0)
Requires-Dist: click (>=8.1.0,<9.0.0)
Requires-Dist: ifpd2q (>=1.0.3,<2.0.0)
Requires-Dist: joblib (>=1,<2)
Requires-Dist: lets-plot (>=4.3.2,<5.0.0)
Requires-Dist: numpy (>=1.20,<2.0)
Requires-Dist: pandas (>=1.2.2,<3.0.0)
Requires-Dist: poetry (>=1.5,<2.0)
Requires-Dist: polars (>=0.20.30,<0.21.0)
Requires-Dist: requests (>=2.31.0,<3.0.0)
Requires-Dist: tabulate (>=0.9.0,<0.10.0)
Requires-Dist: tqdm (>=4,<5)
Project-URL: Repository, https://github.com/qverron/probe_design
